danger_python/__init__.py
danger_python/cli.py
danger_python/danger.py
danger_python/decorators.py
danger_python/exceptions.py
danger_python/generator/__init__.py
danger_python/generator/builder.py
danger_python/generator/models.py
danger_python/generator/parser.py
danger_python/generator/renderer.py
danger_python/generator/templates/dsl.py.jinja
danger_python/models.py
danger_python/plugins.py
danger_python/shell.py
danger_python-0.1.0.dist-info/entry_points.txt
danger_python-0.1.0.dist-info/LICENSE
danger_python-0.1.0.dist-info/WHEEL
danger_python-0.1.0.dist-info/METADATA
danger_python-0.1.0.dist-info/RECORD
