Metadata-Version: 2.1
Name: danger-python
Version: 0.1.0
Summary: Write your Dangerfiles in Python.
License: MIT
Author: Orta Therox
Author-email: danger@orta.io
Requires-Python: >=3.7,<4.0
Classifier: License :: OSI Approved :: MIT License
Classifier: Programming Language :: Python :: 3
Classifier: Programming Language :: Python :: 3.7
Classifier: Programming Language :: Python :: 3.8
Requires-Dist: click (>=7.0,<8.0)
Requires-Dist: click-default-group (>=1.2.2,<2.0.0)
Requires-Dist: pydantic (>=1.4,<2.0)
